bluebeam/Engine.py
bluebeam/Engine2.py
bluebeam/GlobalVars.py
bluebeam/Level.py
bluebeam/TileMap.py
bluebeam/__init__.py
bluebeam/savefile.txt
bluebeam/Sounds/cherish.xm
bluebeam/Sounds/db_ab.xm
bluebeam/Sounds/flc_pamp.mod
bluebeam/Sounds/heidi7.xm
bluebeam/Sounds/moskito.xm
bluebeam/Sounds/trainer5.mod
bluebeam/images/Confusion.png
bluebeam/images/DeathScreen.png
bluebeam/images/HelpButton.png
bluebeam/images/HelpButtonGlow.png
bluebeam/images/MenuButton.png
bluebeam/images/MenuButtonRed.png
bluebeam/images/Options2.png
bluebeam/images/OptionsButton.png
bluebeam/images/OptionsButtonGlow.png
bluebeam/images/Pause.png
bluebeam/images/PauseMenu.png
bluebeam/images/QuitButton.png
bluebeam/images/QuitButtonGlow.png
bluebeam/images/QuitButtonRed.png
bluebeam/images/RestartButton.png
bluebeam/images/RestartButtonRed.png
bluebeam/images/SelectionArrow.png
bluebeam/images/StartButton.png
bluebeam/images/StartButtonGlow.png
bluebeam/images/StartButtonRed.png
bluebeam/images/arm.png
bluebeam/images/armRed.png
bluebeam/images/ball.png
bluebeam/images/ball_red.png
bluebeam/images/boss01_commander.png
bluebeam/images/boss01_core.png
bluebeam/images/boss01_turrets.png
bluebeam/images/commander_gun.png
bluebeam/images/heart.png
bluebeam/images/sigma.png
bluebeam/images/sigmaRed.png
bluebeam/images/testHUD.png
bluebeam/images/testHUD2.png
bluebeam/images/Blue/frame 1.png
bluebeam/images/Blue/frame 2.png
bluebeam/images/Blue/frame 3.png
bluebeam/images/Blue/frame 4.png
bluebeam/images/Blue/frame 5.png
bluebeam/images/Blue/frame 6.png
bluebeam/images/Boss/AlphaWhale/boss01_body.png
bluebeam/images/Boss/BetaSpire/boss02_body.png
bluebeam/images/Boss/BetaSpire/boss02_commander.png
bluebeam/images/Boss/BetaSpire/boss02_core.png
bluebeam/images/Boss/BetaSpire/boss02_extents.png
bluebeam/images/Boss/BetaSpire/boss02_glass.png
bluebeam/images/Boss/BetaSpire/boss02_jets.png
bluebeam/images/Boss/BetaSpire/boss02_streams.png
bluebeam/images/Boss/GammaGenerator/boss03_body.png
bluebeam_rel-4.0.0.dist-info/LICENSE
bluebeam_rel-4.0.0.dist-info/METADATA
bluebeam_rel-4.0.0.dist-info/WHEEL
bluebeam_rel-4.0.0.dist-info/entry_points.txt
bluebeam_rel-4.0.0.dist-info/top_level.txt
bluebeam_rel-4.0.0.dist-info/RECORD
